[
        {
            "id": "1",
            "name": "Bonito",
            "state": "Mato Grosso do Sul",
            "initials": "MS",
            "country": "BR",
            "region": "Centro Oeste",
            "image": "https://acarolsf.github.io/data/lugares/bonito-ms.jpg"
        },
        {
            "id": "2",
            "name": "Alto Paraíso (Chapada dos Veadeiros)",
            "state": "Goiás",
            "initials": "GO",
            "country": "BR",
            "region": "Centro Oeste",
            "image": "https://acarolsf.github.io/data/lugares/alto-paraiso-go.png"
        },
        {
            "id": "3",
            "name": "Pirenópolis",
            "state": "Goiás",
            "initials": "GO",
            "country": "BR",
            "region": "Centro Oeste",
            "image": "https://acarolsf.github.io/data/lugares/pirenopolis-go.png"
        },
        {
            "id": "4",
            "name": "Lençóis (Chapada Diamantina)",
            "state": "Bahia",
            "initials": "BA",
            "country": "BR",
            "region": "Nordeste",
            "image": "https://acarolsf.github.io/data/lugares/lencois-ba.png"
        },
        {
            "id": "5",
            "name": "Fernando de Noronha",
            "state": "Pernambuco",
            "initials": "PE",
            "country": "BR",
            "region": "Nordeste",
            "image": "https://acarolsf.github.io/data/lugares/noronha-pe.png"
        },
        {
            "id": "6",
            "name": "João Pessoa",
            "state": "Paraíba",
            "initials": "PB",
            "country": "BR",
            "region": "Nordeste",
            "image": "https://acarolsf.github.io/data/lugares/joao-pessoa-pb.jpg"
        },
        {
            "id": "7",
            "name": "São Miguel do Gostoso",
            "state": "Rio Grande do Norte",
            "initials": "RN",
            "country": "BR",
            "region": "Nordeste",
            "image": "https://acarolsf.github.io/data/lugares/sao-miguel-do-gostoso-rn.png"
        },
        {
            "id": "8",
            "name": "São Miguel dos Milagres",
            "state": "Alagoas",
            "initials": "AL",
            "country": "BR",
            "region": "Nordeste",
            "image": "https://acarolsf.github.io/data/lugares/sao-miguel-dos-milagres-al.jpg"
        },
        {
            "id": "9",
            "name": "Jericoacoara",
            "state": "Ceará",
            "initials": "CE",
            "country": "BR",
            "region": "Nordeste",
            "image": "https://acarolsf.github.io/data/lugares/jericoacoara-ce.jpg"
        },
        {
            "id": "10",
            "name": "Barra Grande",
            "state": "Bahia",
            "initials": "BA",
            "country": "BR",
            "region": "Nordeste",
            "image": "https://acarolsf.github.io/data/lugares/barra-grande-ba.png"
        },
        {
            "id": "11",
            "name": "Maceió",
            "state": "Alagoas",
            "initials": "AL",
            "country": "BR",
            "region": "Nordeste",
            "image": "https://acarolsf.github.io/data/lugares/maceio-al.png"
        },
        {
            "id": "12",
            "name": "Praia de Pipa (Tibau do Sul)",
            "state": "Rio Grande do Norte",
            "initials": "RN",
            "country": "BR",
            "region": "Nordeste",
            "image": "https://acarolsf.github.io/data/lugares/praia-de-pipa-rn.png"
        },
        {
            "id": "13",
            "name": "Porto de Galinhas (Ipojuca)",
            "state": "Pernambuco",
            "initials": "PE",
            "country": "BR",
            "region": "Nordeste",
            "image": "https://acarolsf.github.io/data/lugares/porto-de-galinhas-pe.jpeg"
        },
        {
            "id": "14",
            "name": "Lençóis Maranhenses",
            "state": "Maranhão",
            "initials": "MA",
            "country": "BR",
            "region": "Nordeste",
            "image": "https://acarolsf.github.io/data/lugares/lencois-maranhenses-ma.png"
        },
        {
            "id": "15",
            "name": "Itacaré",
            "state": "Bahia",
            "initials": "BA",
            "country": "BR",
            "region": "Nordeste",
            "image": "https://acarolsf.github.io/data/lugares/itacare-ba.jpeg"
        },
        {
            "id": "16",
            "name": "Arraial d'Ajuda (Porto Seguro)",
            "state": "Bahia",
            "initials": "BA",
            "country": "BR",
            "region": "Nordeste",
            "image": "https://acarolsf.github.io/data/lugares/arraial-dajuda-ba.png"
        },
        {
            "id": "17",
            "name": "Morro de São Paulo",
            "state": "Bahia",
            "initials": "BA",
            "country": "BR",
            "region": "Nordeste",
            "image": "https://acarolsf.github.io/data/lugares/morro-de-sao-paulo-ba.png"
        },
        {
            "id": "18",
            "name": "Tamandaré",
            "state": "Pernambuco",
            "initials": "PE",
            "country": "BR",
            "region": "Nordeste",
            "image": "https://acarolsf.github.io/data/lugares/tamandare-pe.png"
        },
        {
            "id": "19",
            "name": "Maragogi",
            "state": "Alagoas",
            "initials": "AL",
            "country": "BR",
            "region": "Nordeste",
            "image": "https://acarolsf.github.io/data/lugares/maragogi-al.png"
        },
        {
            "id": "20",
            "name": "Aracaju",
            "state": "Sergipe",
            "initials": "SE",
            "country": "BR",
            "region": "Nordeste",
            "image": "https://acarolsf.github.io/data/lugares/aracaju-se.jpg"
        },
        {
            "id": "21",
            "name": "Praia do Forte (Mata de São João)",
            "state": "Bahia",
            "initials": "BA",
            "country": "BR",
            "region": "Nordeste",
            "image": "https://acarolsf.github.io/data/lugares/praia-do-forte-ba.jpg"
        },
        {
            "id": "22",
            "name": "Caraíva (Porto Seguro)",
            "state": "Bahia",
            "initials": "BA",
            "country": "BR",
            "region": "Nordeste",
            "image": "https://acarolsf.github.io/data/lugares/caraiva-ba.png"
        },
        {
            "id": "23",
            "name": "Natal",
            "state": "Rio Grande do Norte",
            "initials": "RN",
            "country": "BR",
            "region": "Nordeste",
            "image": "https://acarolsf.github.io/data/lugares/natal-rn.png"
        },
        {
            "id": "24",
            "name": "Trancoso",
            "state": "Bahia",
            "initials": "BA",
            "country": "BR",
            "region": "Nordeste",
            "image": "https://acarolsf.github.io/data/lugares/trancoso-ba.jpg"
        },
        {
            "id": "25",
            "name": "Olinda",
            "state": "Pernambuco",
            "initials": "PE",
            "country": "BR",
            "region": "Nordeste",
            "image": "https://acarolsf.github.io/data/lugares/olinda-pe.jpeg"
        },
        {
            "id": "26",
            "name": "Jalapão",
            "state": "Tocantins",
            "initials": "TO",
            "country": "BR",
            "region": "Norte",
            "image": "https://acarolsf.github.io/data/lugares/jalapao-to.jpg"
        },
        {
            "id": "27",
            "name": "Alter do Chão (Santarém)",
            "state": "Pará",
            "initials": "PA",
            "country": "BR",
            "region": "Norte",
            "image": "https://acarolsf.github.io/data/lugares/alter-do-chao-pa.png"
        },
        {
            "id": "28",
            "name": "Manaus",
            "state": "Amazonas",
            "initials": "AM",
            "country": "BR",
            "region": "Norte",
            "image": "https://acarolsf.github.io/data/lugares/manaus-am.jpg"
        },
        {
            "id": "29",
            "name": "Tiradentes",
            "state": "Minas Gerais",
            "initials": "MG",
            "country": "BR",
            "region": "Sudeste",
            "image": "https://acarolsf.github.io/data/lugares/tiradentes-mg.png"
        },
        {
            "id": "30",
            "name": "Ouro Preto",
            "state": "Minas Gerais",
            "initials": "MG",
            "country": "BR",
            "region": "Sudeste",
            "image": "https://acarolsf.github.io/data/lugares/ouro-preto-mg.jpg"
        },
        {
            "id": "31",
            "name": "Poço de Caldas",
            "state": "Minas Gerais",
            "initials": "MG",
            "country": "BR",
            "region": "Sudeste",
            "image": "https://acarolsf.github.io/data/lugares/pocos-de-caldas-go.png"
        },
        {
            "id": "32",
            "name": "Inhotim (Brumadinho)",
            "state": "Minas Gerais",
            "initials": "MG",
            "country": "BR",
            "region": "Sudeste",
            "image": "https://acarolsf.github.io/data/lugares/inhotim-mg.jpeg"
        },
        {
            "id": "33",
            "name": "Visconde de Mauá",
            "state": "Rio de Janeiro",
            "initials": "RJ",
            "country": "BR",
            "region": "Sudeste",
            "image": "https://acarolsf.github.io/data/lugares/visconde-de-maua-rj.png"
        },
        {
            "id": "34",
            "name": "Monte Verde",
            "state": "Minas Gerais",
            "initials": "MG",
            "country": "BR",
            "region": "Sudeste",
            "image": "https://acarolsf.github.io/data/lugares/monte-verde-mg.jpg"
        },
        {
            "id": "35",
            "name": "Paraty",
            "state": "Rio de Janeiro",
            "initials": "RJ",
            "country": "BR",
            "region": "Sudeste",
            "image": "https://acarolsf.github.io/data/lugares/paraty-rj.png"
        },
        {
            "id": "36",
            "name": "Olímpia",
            "state": "São Paulo",
            "initials": "SP",
            "country": "BR",
            "region": "Sudeste",
            "image": "https://acarolsf.github.io/data/lugares/olimpia-sp.jpg"
        },
        {
            "id": "37",
            "name": "Brotas",
            "state": "São Paulo",
            "initials": "SP",
            "country": "BR",
            "region": "Sudeste",
            "image": "https://acarolsf.github.io/data/lugares/brotas-sp.png"
        },
        {
            "id": "38",
            "name": "Belo Horizonte",
            "state": "Minas Gerais",
            "initials": "MG",
            "country": "BR",
            "region": "Sudeste",
            "image": "https://acarolsf.github.io/data/lugares/belo-horizonte-mg.png"
        },
        {
            "id": "39",
            "name": "Petrópolis",
            "state": "Rio de Janeiro",
            "initials": "RJ",
            "country": "BR",
            "region": "Sudeste",
            "image": "https://acarolsf.github.io/data/lugares/petropolis-rj.png"
        },
        {
            "id": "40",
            "name": "Ilha Grande",
            "state": "Rio de Janeiro",
            "initials": "RJ",
            "country": "BR",
            "region": "Sudeste",
            "image": "https://acarolsf.github.io/data/lugares/ilha-grande-rj.jpg"
        },
        {
            "id": "41",
            "name": "Gramado",
            "state": "Rio Grande do Sul",
            "initials": "RS",
            "country": "BR",
            "region": "Sul",
            "image": "https://acarolsf.github.io/data/lugares/gramado-rs.jpeg"
        },
        {
            "id": "42",
            "name": "Bento Gonçalves",
            "state": "Rio Grande do Sul",
            "initials": "RS",
            "country": "BR",
            "region": "Sul",
            "image": "https://acarolsf.github.io/data/lugares/bento-goncalves-rs.jpg"
        },
        {
            "id": "43",
            "name": "Pomerode",
            "state": "Santa Catarina",
            "initials": "SC",
            "country": "BR",
            "region": "Sul",
            "image": "https://acarolsf.github.io/data/lugares/pomedore-sc.jpg"
        },
        {
            "id": "44",
            "name": "Canela",
            "state": "Rio Grande do Sul",
            "initials": "RS",
            "country": "BR",
            "region": "Sul",
            "image": "https://acarolsf.github.io/data/lugares/canela-rs.png"
        },
        {
            "id": "45",
            "name": "Florianópolis",
            "state": "Santa Catarina",
            "initials": "SC",
            "country": "BR",
            "region": "Sul",
            "image": "https://acarolsf.github.io/data/lugares/florianopolis-sc.png"
        },
        {
            "id": "46",
            "name": "Blumenau",
            "state": "Santa Catarina",
            "initials": "SC",
            "country": "BR",
            "region": "Sul",
            "image": "https://acarolsf.github.io/data/lugares/blumenau-sc.jpg"
        },
        {
            "id": "47",
            "name": "Urubici",
            "state": "Santa Catarina",
            "initials": "SC",
            "country": "BR",
            "region": "Sul",
            "image": "https://acarolsf.github.io/data/lugares/urubici-sc.png"
        },
        {
            "id": "48",
            "name": "Foz do Iguaçu",
            "state": "Paraná",
            "initials": "PR",
            "country": "BR",
            "region": "Sul",
            "image": "https://acarolsf.github.io/data/lugares/foz-do-iguacu-pr.png"
        },
        {
            "id": "49",
            "name": "Curitiba",
            "state": "Paraná",
            "initials": "PR",
            "country": "BR",
            "region": "Sul",
            "image": "https://acarolsf.github.io/data/lugares/curitiba-pr.jpg"
        },
        {
            "id": "50",
            "name": "Cambará do Sul",
            "state": "Rio Grande do Sul",
            "initials": "RS",
            "country": "BR",
            "region": "Sul",
            "image": "https://acarolsf.github.io/data/lugares/cambara-do-sul-rs.png"
        }
]